luna/__init__.py
luna/full_devices.py
luna/usb2.py
luna/usb3.py
luna/gateware/__init__.py
luna/gateware/memory.py
luna/gateware/applets/__init__.py
luna/gateware/applets/speed_test.py
luna/gateware/architecture/__init__.py
luna/gateware/architecture/car.py
luna/gateware/architecture/flash_sn.py
luna/gateware/debug/__init__.py
luna/gateware/debug/console.py
luna/gateware/debug/ila.py
luna/gateware/interface/__init__.py
luna/gateware/interface/flash.py
luna/gateware/interface/i2c.py
luna/gateware/interface/jtag.py
luna/gateware/interface/pipe.py
luna/gateware/interface/psram.py
luna/gateware/interface/spi.py
luna/gateware/interface/uart.py
luna/gateware/interface/ulpi.py
luna/gateware/interface/utmi.py
luna/gateware/interface/gateware_phy/__init__.py
luna/gateware/interface/gateware_phy/phy.py
luna/gateware/interface/gateware_phy/receiver.py
luna/gateware/interface/gateware_phy/transmitter.py
luna/gateware/interface/serdes_phy/__init__.py
luna/gateware/interface/serdes_phy/ecp5.py
luna/gateware/interface/serdes_phy/lfps.py
luna/gateware/interface/serdes_phy/xc7.py
luna/gateware/interface/serdes_phy/xc7_gtp.py
luna/gateware/interface/serdes_phy/xc7_gtx.py
luna/gateware/platform/__init__.py
luna/gateware/platform/core.py
luna/gateware/platform/toolchain.py
luna/gateware/stream/__init__.py
luna/gateware/stream/arbiter.py
luna/gateware/stream/future.py
luna/gateware/stream/generator.py
luna/gateware/test/__init__.py
luna/gateware/test/usb2.py
luna/gateware/test/utils.py
luna/gateware/test/contrib/__init__.py
luna/gateware/test/contrib/crc.py
luna/gateware/test/contrib/usb_packet.py
luna/gateware/usb/__init__.py
luna/gateware/usb/device.py
luna/gateware/usb/stream.py
luna/gateware/usb/devices/__init__.py
luna/gateware/usb/devices/acm.py
luna/gateware/usb/devices/ila.py
luna/gateware/usb/request/__init__.py
luna/gateware/usb/request/control.py
luna/gateware/usb/request/interface.py
luna/gateware/usb/request/standard.py
luna/gateware/usb/request/windows/__init__.py
luna_usb-0.2.3.dist-info/licenses/LICENSE
luna_usb-0.2.3.dist-info/METADATA
luna_usb-0.2.3.dist-info/WHEEL
luna_usb-0.2.3.dist-info/top_level.txt
luna_usb-0.2.3.dist-info/RECORD
