Metadata-Version: 2.4
Name: luna-usb
Version: 0.2.3
Summary: Amaranth HDL framework for FPGA-based USB solutions
Author-email: Great Scott Gadgets <dev@greatscottgadgets.com>
License: BSD
Project-URL: Documentation, https://luna.readthedocs.io
Project-URL: Repository, https://github.com/greatscottgadgets/luna
Project-URL: Issues, https://github.com/greatscottgadgets/luna/issues
Classifier: Development Status :: 4 - Beta
Classifier: Programming Language :: Python :: 3
Classifier: License :: OSI Approved :: BSD License
Classifier: Operating System :: OS Independent
Classifier: Natural Language :: English
Classifier: Environment :: Console
Classifier: Environment :: Other Environment
Classifier: Intended Audience :: Developers
Classifier: Intended Audience :: Science/Research
Classifier: Topic :: Scientific/Engineering :: Electronic Design Automation (EDA)
Classifier: Topic :: Security
Classifier: Topic :: System :: Hardware :: Universal Serial Bus (USB)
Requires-Python: >=3.9
License-File: LICENSE
Requires-Dist: libusb1>1.9.2
Requires-Dist: pyserial>=3.5
Requires-Dist: pyusb>1.1.1
Requires-Dist: pyvcd>=0.2.4
Requires-Dist: amaranth~=0.5.0
Requires-Dist: usb-protocol~=0.9.2
Provides-Extra: dev
Requires-Dist: apollo_fpga; extra == "dev"
Requires-Dist: prompt-toolkit>3.0.16; extra == "dev"
Dynamic: license-file
